LICENSE
MANIFEST.in
README.rst
setup.py
TWCB/__init__.py
TWCB/fetch.py
TWCB/get.py
TWCB/search.py
TWCB/utils.py
TWCB.egg-info/PKG-INFO
TWCB.egg-info/SOURCES.txt
TWCB.egg-info/dependency_links.txt
TWCB.egg-info/requires.txt
TWCB.egg-info/top_level.txt
tests/__init__.py
tests/context.py
tests/test_fetch.py