Metadata-Version: 2.1
Name: TWCB
Version: 0.1.1
Summary: Third API for TWCB
Home-page: https://github.com/TwQin0403/TWCB
Author: Qin Wei Zhi
Author-email: p300053000qin@gmail.com
License: Copyright (c) 2020, Qin,Wei-Zhi
